palehacker/Main.py
palehacker/__init__.py
palehacker-0.0.4.dist-info/LICENSE
palehacker-0.0.4.dist-info/METADATA
palehacker-0.0.4.dist-info/WHEEL
palehacker-0.0.4.dist-info/top_level.txt
palehacker-0.0.4.dist-info/RECORD
