Metadata-Version: 2.1
Name: palehacker
Version: 0.0.4
Summary: Simple Package
Home-page: https://github.com/Pale-Hacker/PaleHacker-PyPi
Author: PaleHacker
License: UNKNOWN
Keywords: python,proxies,api,requests
Platform: UNKNOWN
Classifier: Programming Language :: Python :: 3
License-File: LICENSE
Requires-Dist: requests
